{
  "trained_at": "2026-04-13T05:08:48.680446",
  "objective": "next_day_direction",
  "target_type": "direction",
  "feature_config": {
    "include_technical": true,
    "include_lags": true,
    "include_regime": false,
    "include_candlesticks": false,
    "lag_periods": [
      1,
      2,
      3,
      5,
      10
    ]
  },
  "lookback_days": 756,
  "training_horizon": 1,
  "horizons": [
    1
  ],
  "test_size": 0.2,
  "validation_size": 0.1,
  "serving_mode": "next_day_direction_classifier",
  "monitoring": {
    "retrain_threshold_hours": 24,
    "stale_after_hours": 24
  },
  "preprocessing": {
    "scaler_type": "minmax",
    "sequence_length": 60
  },
  "split_sizes": {
    "train": 223,
    "validation": 32,
    "test": 64
  },
  "samples": 319,
  "training_sample_count": 223,
  "features": 59,
  "feature_count": 59,
  "params": {},
  "metrics": {
    "validation": {
      "accuracy": 0.5,
      "precision": 0.5789473684210527,
      "recall": 0.5789473684210527,
      "f1": 0.5789473684210527,
      "directional_accuracy": 0.5,
      "roc_auc": 0.42510121457489874,
      "positive_rate": 0.40625,
      "average_probability_up": 0.4914165437221527
    },
    "test": {
      "accuracy": 0.546875,
      "precision": 0.4418604651162791,
      "recall": 0.7916666666666666,
      "f1": 0.5671641791044776,
      "directional_accuracy": 0.546875,
      "roc_auc": 0.6197916666666667,
      "positive_rate": 0.609375,
      "average_probability_up": 0.5879248976707458
    }
  },
  "backtest": {
    "validation": {
      "strategy_return": 0.09949231147766113,
      "benchmark_return": 0.1603546142578125,
      "trade_days": 13,
      "long_ratio": 0.40625,
      "win_rate": 0.5384615384615384
    },
    "test": {
      "strategy_return": -0.05642598867416382,
      "benchmark_return": NaN,
      "trade_days": 39,
      "long_ratio": 0.609375,
      "win_rate": 0.4358974358974359
    },
    "rule": "long_when_probability_up_at_least_0.55_else_flat"
  },
  "version_id": "xgboost_F_h1_20260413_050848",
  "model_type": "xgboost",
  "symbol": "F",
  "training_symbol": "F",
  "horizon": 1,
  "feature_columns": [
    "Returns",
    "Log_Returns",
    "SMA_20",
    "SMA_50",
    "SMA_200",
    "EMA_12",
    "EMA_26",
    "EMA_50",
    "MACD",
    "MACD_Signal",
    "MACD_Histogram",
    "ADX",
    "Ichimoku_A",
    "Ichimoku_B",
    "RSI",
    "Stoch_K",
    "Stoch_D",
    "Williams_R",
    "ROC",
    "Ultimate_Osc",
    "TSI",
    "ATR",
    "BB_High",
    "BB_Mid",
    "BB_Low",
    "BB_Width",
    "BB_Pband",
    "KC_High",
    "KC_Low",
    "DC_High",
    "DC_Low",
    "OBV",
    "CMF",
    "MFI",
    "VWAP",
    "Volume_SMA_20",
    "Volume_Ratio",
    "Daily_Return",
    "Log_Return",
    "High_Low_Range",
    "Open_Close_Range",
    "Close_Lag_1",
    "Return_Lag_1",
    "Volume_Lag_1",
    "Close_Lag_2",
    "Return_Lag_2",
    "Volume_Lag_2",
    "Close_Lag_3",
    "Return_Lag_3",
    "Volume_Lag_3",
    "Close_Lag_5",
    "Return_Lag_5",
    "Volume_Lag_5",
    "Close_Lag_10",
    "Return_Lag_10",
    "Volume_Lag_10",
    "DayOfWeek",
    "Month",
    "Quarter"
  ],
  "bundle_layout": "canonical_symbol_model",
  "bundle_dir": "models\\bundles\\F\\xgboost",
  "artifact_dir": "models\\bundles\\F\\xgboost",
  "model_path": "models\\bundles\\F\\xgboost\\model.json",
  "scaler_path": "models\\bundles\\F\\xgboost\\scaler.joblib",
  "feature_columns_path": "models\\bundles\\F\\xgboost\\feature_columns.json"
}